pybashify/__init__.py
pybashify/constants.py
pybashify/cli/__init__.py
pybashify/cli/main.py
pybashify/compilation/__init__.py
pybashify/compilation/compiler.py
pybashify/compilation/inlines.py
pybashify/compilation/schemas.py
pybashify/compilation/utils.py
pybashify-0.1.1.dist-info/METADATA
pybashify-0.1.1.dist-info/WHEEL
pybashify-0.1.1.dist-info/entry_points.txt
pybashify-0.1.1.dist-info/licenses/LICENSE
pybashify-0.1.1.dist-info/RECORD
