Metadata-Version: 2.3
Name: pybashify
Version: 0.1.1
Summary: Use Python to write bash scripts while interop w/ bash
Project-URL: Repository, https://github.com/AmeerArsala/pybashify
Project-URL: Source, https://github.com/AmeerArsala/pybashify
Project-URL: Tracker, https://github.com/AmeerArsala/pybashify/issues
Author-email: Ameer Arsala <ameer.arsala03@gmail.com>
License:                                  Apache License
License-File: LICENSE
Requires-Python: >=3.10
Requires-Dist: astor<0.9,>=0.8.1
Requires-Dist: numpy<3,>=2.1.0
Requires-Dist: pydantic>=2.0
Requires-Dist: typer<0.13,>=0.12.5
Provides-Extra: fdev
Requires-Dist: hatch; extra == 'fdev'
Requires-Dist: pytest; extra == 'fdev'
Requires-Dist: ruff<0.7,>=0.6.5; extra == 'fdev'
Requires-Dist: tomli<3,>=2.0.2; extra == 'fdev'
